{
    "code": "0",
    "msg": "success",
    "version": "4.0",
    "timestamp": 1543898948000,
    "data": {
        "total": 5,
        "data": [
            {
                "title": "泡洋葱",
                "description": "功效太强，直接防癌抗癌",
                "image": "http://img.szzhangchu.com/1439346243258_8120836910.jpg",
                "id": "252",
                "video": "http://video.szzhangchu.com/paoyangcongA.mp4",
                "video1": "http://video.szzhangchu.com/paoyangcongB.mp4",
                "play": "43418",
                "favorite": "1680",
                "create_date": 1036993301,
                "content": "洋葱含有丰富的硒元素，有延缓衰老的作用。吃过了太多的洋葱炒蛋，洋葱啥啥啥，这次研制一道泡洋葱，增加一种全新的体验，丰富一下人生。",
                "tags_info": [
                    {
                        "id": "324",
                        "text": "腌",
                        "type": 1
                    },
                    {
                        "id": "159",
                        "text": "根茎类",
                        "type": 1
                    },
                    {
                        "id": "300",
                        "text": "降低血脂",
                        "type": 1
                    },
                    {
                        "id": "144",
                        "text": "蔬菜",
                        "type": 1
                    },
                    {
                        "id": "319",
                        "text": "辣",
                        "type": 1
                    }
                ]
            },
            {
                "title": "辣味胡萝卜泡菜",
                "description": "浓浓混合香",
                "image": "http://img.szzhangchu.com/1439365185564_6669537701.jpg",
                "id": "1750",
                "video": "http://video.szzhangchu.com/laweihuluobopaocaiA.mp4",
                "video1": "http://video.szzhangchu.com/laweihuluobopaocaiB.mp4",
                "play": "2650",
                "favorite": "306",
                "create_date": 1078460805,
                "content": "胡萝卜泡菜要做的好，生姜、花椒、八角和青红椒，样样不可少，还有白酒，再随个人喜好加入调料，耐心等一周，美味就来喽!",
                "tags_info": [
                    {
                        "id": "144",
                        "text": "蔬菜",
                        "type": 1
                    },
                    {
                        "id": "159",
                        "text": "根茎类",
                        "type": 1
                    },
                    {
                        "id": "319",
                        "text": "辣",
                        "type": 1
                    },
                    {
                        "id": "163",
                        "text": "瓜果类",
                        "type": 1
                    },
                    {
                        "id": "324",
                        "text": "腌",
                        "type": 1
                    }
                ]
            },
            {
                "title": "五香洋葱泡菜",
                "description": "开胃又杀菌的餐前小菜",
                "image": "http://img.szzhangchu.com/1439365213204_3139515066.jpg",
                "id": "1752",
                "video": "http://video.szzhangchu.com/wuxiangyangcongpaocaiA.mp4",
                "video1": "http://video.szzhangchu.com/wuxiangyangcongpaocaiB.mp4",
                "play": "2895",
                "favorite": "84",
                "create_date": 1078544678,
                "content": "洋葱有功能强大的杀菌作用，常吃令身体健康少生病，它强烈的辛香味能促进食欲，想提高食欲战斗力，餐前就得吃它。",
                "tags_info": [
                    {
                        "id": "324",
                        "text": "腌",
                        "type": 1
                    },
                    {
                        "id": "295",
                        "text": "开胃消食",
                        "type": 1
                    },
                    {
                        "id": "159",
                        "text": "根茎类",
                        "type": 1
                    },
                    {
                        "id": "144",
                        "text": "蔬菜",
                        "type": 1
                    },
                    {
                        "id": "319",
                        "text": "辣",
                        "type": 1
                    }
                ]
            },
            {
                "title": "辣味玉米笋",
                "description": "下饭的玉米崽子",
                "image": "http://img.szzhangchu.com/1439366201695_8739445031.jpg",
                "id": "1788",
                "video": "http://video.szzhangchu.com/laweiyumisunA.mp4",
                "video1": "http://video.szzhangchu.com/laweiyumisunB.mp4",
                "play": "3298",
                "favorite": "414",
                "create_date": 1079502587,
                "content": "玉米笋口感甜脆，鲜嫩可口，和辣椒一块炒，香辣助食欲，还可以帮助消脂哦。",
                "tags_info": [
                    {
                        "id": "123",
                        "text": "素菜",
                        "type": 1
                    },
                    {
                        "id": "319",
                        "text": "辣",
                        "type": 1
                    },
                    {
                        "id": "144",
                        "text": "蔬菜",
                        "type": 1
                    },
                    {
                        "id": "300",
                        "text": "降低血脂",
                        "type": 1
                    },
                    {
                        "id": "159",
                        "text": "根茎类",
                        "type": 1
                    }
                ]
            },
            {
                "title": "辣椒莴笋片",
                "description": "简单小菜轻松做",
                "image": "http://img.szzhangchu.com/1439459716256_3168432565.jpg",
                "id": "1916",
                "video": "http://video.szzhangchu.com/lajiaowosunpianA.mp4",
                "video1": "http://video.szzhangchu.com/lajiaowosunpianB.mp4",
                "play": "3005",
                "favorite": "300",
                "create_date": 1083052778,
                "content": "莴笋含有大量的钾和烟酸，有利水的功效，加入辣椒腌渍入味后更是开胃下饭，再配上爽脆的口感，也是香脆好滋味。",
                "tags_info": [
                    {
                        "id": "319",
                        "text": "辣",
                        "type": 1
                    },
                    {
                        "id": "324",
                        "text": "腌",
                        "type": 1
                    },
                    {
                        "id": "295",
                        "text": "开胃消食",
                        "type": 1
                    },
                    {
                        "id": "159",
                        "text": "根茎类",
                        "type": 1
                    },
                    {
                        "id": "144",
                        "text": "蔬菜",
                        "type": 1
                    }
                ]
            }
        ]
    }
}